rubti_beancount_import/__init__.py
rubti_beancount_import/bbva.py
rubti_beancount_import/giro.py
rubti_beancount_import/master_card.py
rubti_beancount_import/myinvestor.py
rubti_beancount_import/utils.py
rubti_beancount_import-1.2.dist-info/licenses/LICENSE
rubti_beancount_import-1.2.dist-info/METADATA
rubti_beancount_import-1.2.dist-info/WHEEL
rubti_beancount_import-1.2.dist-info/top_level.txt
rubti_beancount_import-1.2.dist-info/RECORD
