Metadata-Version: 2.4
Name: rubti_beancount_import
Version: 1.2
Summary: Beancount importers for various CSV formats
Author: Thilo Wendt
Project-URL: Repository, https://github.com/rubti/beancount-import
Keywords: beancount,sparkasse,bbva,edenred
Classifier: Programming Language :: Python
Classifier: Development Status :: 5 - Production/Stable
Classifier: Intended Audience :: Developers
Classifier: Intended Audience :: End Users/Desktop
Classifier: Natural Language :: English
Classifier: Topic :: Office/Business :: Financial :: Accounting
Classifier: Typing :: Typed
Requires-Python: >=3
License-File: LICENSE
Requires-Dist: beancount<=3.2
Requires-Dist: beangulp
Requires-Dist: pandas
Requires-Dist: openpyxl
Requires-Dist: identify
Requires-Dist: pyyaml
Provides-Extra: dev
Requires-Dist: black; extra == "dev"
Requires-Dist: isort; extra == "dev"
Requires-Dist: pre-commit; extra == "dev"
Dynamic: license-file
